MANIFEST.in
readme.md
setup.py
docs/.docs.md
docs/hello.md
nyuwa/__init__.py
nyuwa/constant.py
nyuwa/content.py
nyuwa/hello.py
nyuwa/util.py
nyuwa.egg-info/PKG-INFO
nyuwa.egg-info/SOURCES.txt
nyuwa.egg-info/dependency_links.txt
nyuwa.egg-info/requires.txt
nyuwa.egg-info/top_level.txt
nyuwa/algo/__init__.py
nyuwa/algo/geopandas.py
nyuwa/algo/quadTree.py