Metadata-Version: 2.1
Name: nyuwa
Version: 0.0.5
Summary: GIS 算法
Home-page: https://github.com/
Author: gisok
Author-email: gisok@126.com
License: MIT Licence
Keywords: pip,nyuwa,featureextraction
Platform: any
Requires-Python: >=3.5.0
